odoo/addons/partner_supplier_ref/README.rst
odoo/addons/partner_supplier_ref/__init__.py
odoo/addons/partner_supplier_ref/__manifest__.py
odoo/addons/partner_supplier_ref/i18n/ca_ES.po
odoo/addons/partner_supplier_ref/i18n/es.po
odoo/addons/partner_supplier_ref/i18n/it.po
odoo/addons/partner_supplier_ref/i18n/partner_supplier_ref.pot
odoo/addons/partner_supplier_ref/models/__init__.py
odoo/addons/partner_supplier_ref/models/res_partner.py
odoo/addons/partner_supplier_ref/readme/CONTRIBUTORS.md
odoo/addons/partner_supplier_ref/readme/DESCRIPTION.md
odoo/addons/partner_supplier_ref/static/description/icon.png
odoo/addons/partner_supplier_ref/static/description/index.html
odoo/addons/partner_supplier_ref/tests/__init__.py
odoo/addons/partner_supplier_ref/tests/test_partner_supplier_ref.py
odoo/addons/partner_supplier_ref/views/res_partner_view.xml
odoo_addon_partner_supplier_ref-19.0.1.0.0.5.dist-info/METADATA
odoo_addon_partner_supplier_ref-19.0.1.0.0.5.dist-info/WHEEL
odoo_addon_partner_supplier_ref-19.0.1.0.0.5.dist-info/top_level.txt
odoo_addon_partner_supplier_ref-19.0.1.0.0.5.dist-info/RECORD
